<annotation>
	<folder>camera</folder>
	<filename>444.jpg</filename>
	<path>C:\Users\etesam\Desktop\od\Tensorflow\workspace\images\collectedimages\camera\444.jpg</path>
	<source>
		<database>Unknown</database>
	</source>
	<size>
		<width>275</width>
		<height>183</height>
		<depth>3</depth>
	</size>
	<segmented>0</segmented>
	<object>
		<name>Camera</name>
		<pose>Unspecified</pose>
		<truncated>0</truncated>
		<difficult>0</difficult>
		<bndbox>
			<xmin>154</xmin>
			<ymin>73</ymin>
			<xmax>195</xmax>
			<ymax>108</ymax>
		</bndbox>
	</object>
</annotation>
